edman/__init__.py
edman/config.py
edman/convert.py
edman/db.py
edman/exceptions.py
edman/file.py
edman/json_manager.py
edman/py.typed
edman/search.py
edman/utils.py
tests/ini/test_db.ini.sample
venv/bin/jp.py
edman-2025.1.31.dist-info/LICENSE.txt
edman-2025.1.31.dist-info/METADATA
edman-2025.1.31.dist-info/WHEEL
edman-2025.1.31.dist-info/top_level.txt
edman-2025.1.31.dist-info/RECORD
