Metadata-Version: 2.2
Name: edman
Version: 2025.1.31
Summary: KEK IMSS SBRC/PF Experimental Data Management System
Author-email: Masaki Ohno <masakio@post.kek.jp>
License: MIT License
Project-URL: documentation, https://ryde.github.io/edman/
Project-URL: repository, https://github.com/ryde/edman
Classifier: Programming Language :: Python :: 3
Classifier: Programming Language :: Python :: 3.12
Classifier: License :: OSI Approved :: MIT License
Classifier: Topic :: Database :: Front-Ends
Requires-Python: >=3.12
License-File: LICENSE.txt
Requires-Dist: pymongo>=4.11
Requires-Dist: python-dateutil>=2.9.0.post0
Requires-Dist: jmespath>=1.0.1
